{"2019-10-25": {"current_date": "2019-10-25", "previous_date": "2019-10-25", "commitCount": 83, "issueCount": 42, "openIssueCount": 14, "closedIssueCount": 28, "pullRequestCount": 4, "openPullRequestCount": 0, "mergedPullRequestCount": 4, "closedPullRequestCount": 0, "forkCount": 30, "starCount": 77, "watcherCount": 24}, "2019-10-27": {"current_date": "2019-10-27", "previous_date": "2019-10-27", "commitCount": 83, "issueCount": 43, "openIssueCount": 15, "closedIssueCount": 28, "pullRequestCount": 4, "openPullRequestCount": 0, "mergedPullRequestCount": 4, "closedPullRequestCount": 0, "forkCount": 30, "starCount": 77, "watcherCount": 24}, "2019-11-03": {"current_date": "2019-11-03", "previous_date": "2019-11-03", "commitCount": 89, "issueCount": 43, "openIssueCount": 15, "closedIssueCount": 28, "pullRequestCount": 4, "openPullRequestCount": 0, "mergedPullRequestCount": 4, "closedPullRequestCount": 0, "forkCount": 32, "starCount": 82, "watcherCount": 24}, "2019-11-10": {"current_date": "2019-11-10", "previous_date": "2019-11-10", "commitCount": 89, "issueCount": 43, "openIssueCount": 15, "closedIssueCount": 28, "pullRequestCount": 4, "openPullRequestCount": 0, "mergedPullRequestCount": 4, "closedPullRequestCount": 0, "forkCount": 32, "starCount": 83, "watcherCount": 24}, "2019-11-17": {"current_date": "2019-11-17", "previous_date": "2019-11-17", "commitCount": 89, "issueCount": 43, "openIssueCount": 15, "closedIssueCount": 28, "pullRequestCount": 4, "openPullRequestCount": 0, "mergedPullRequestCount": 4, "closedPullRequestCount": 0, "forkCount": 33, "starCount": 83, "watcherCount": 24}, "2019-11-24": {"current_date": "2019-11-24", "previous_date": "2019-11-24", "commitCount": 89, "issueCount": 44, "openIssueCount": 16, "closedIssueCount": 28, "pullRequestCount": 4, "openPullRequestCount": 0, "mergedPullRequestCount": 4, "closedPullRequestCount": 0, "forkCount": 34, "starCount": 83, "watcherCount": 24}, "2019-12-01": {"current_date": "2019-12-01", "previous_date": "2019-12-01", "commitCount": 89, "issueCount": 44, "openIssueCount": 16, "closedIssueCount": 28, "pullRequestCount": 4, "openPullRequestCount": 0, "mergedPullRequestCount": 4, "closedPullRequestCount": 0, "forkCount": 35, "starCount": 88, "watcherCount": 24}, "2019-12-08": {"current_date": "2019-12-08", "previous_date": "2019-12-08", "commitCount": 89, "issueCount": 45, "openIssueCount": 17, "closedIssueCount": 28, "pullRequestCount": 4, "openPullRequestCount": 0, "mergedPullRequestCount": 4, "closedPullRequestCount": 0, "forkCount": 35, "starCount": 89, "watcherCount": 24}, "2019-12-15": {"current_date": "2019-12-15", "previous_date": "2019-12-15", "commitCount": 89, "issueCount": 45, "openIssueCount": 17, "closedIssueCount": 28, "pullRequestCount": 4, "openPullRequestCount": 0, "mergedPullRequestCount": 4, "closedPullRequestCount": 0, "forkCount": 35, "starCount": 89, "watcherCount": 24}, "2019-12-22": {"current_date": "2019-12-22", "previous_date": "2019-12-22", "commitCount": 89, "issueCount": 45, "openIssueCount": 17, "closedIssueCount": 28, "pullRequestCount": 4, "openPullRequestCount": 0, "mergedPullRequestCount": 4, "closedPullRequestCount": 0, "forkCount": 36, "starCount": 91, "watcherCount": 24}, "2019-12-29": {"current_date": "2019-12-29", "previous_date": "2019-12-29", "commitCount": 89, "issueCount": 45, "openIssueCount": 17, "closedIssueCount": 28, "pullRequestCount": 4, "openPullRequestCount": 0, "mergedPullRequestCount": 4, "closedPullRequestCount": 0, "forkCount": 36, "starCount": 91, "watcherCount": 24}, "2020-01-05": {"current_date": "2020-01-05", "previous_date": "2020-01-05", "commitCount": 89, "issueCount": 45, "openIssueCount": 17, "closedIssueCount": 28, "pullRequestCount": 4, "openPullRequestCount": 0, "mergedPullRequestCount": 4, "closedPullRequestCount": 0, "forkCount": 37, "starCount": 94, "watcherCount": 24}}